agushuju/__init__.py
agushuju/client.py
agushuju-0.1.3.dist-info/licenses/LICENSE
aigushuju/__init__.py
agushuju-0.1.3.dist-info/METADATA
agushuju-0.1.3.dist-info/WHEEL
agushuju-0.1.3.dist-info/top_level.txt
agushuju-0.1.3.dist-info/RECORD
