Metadata-Version: 2.4
Name: agushuju
Version: 0.1.3
Summary: 爱股数据（别名：A股数据），一个集A股、期货与一体的量化交易数据服务平台。
Home-page: https://github.com/agukeji/agushuju
Author: 安徽爱股科技有限公司
Author-email: 安徽爱股科技有限公司 <jinguxun@qq.com>
License: MIT
Project-URL: Homepage, https://github.com/agukeji/agushuju
Keywords: agushuju,爱股数据,A股数据,aigushuju,agudata,api,sdk,token
Classifier: Programming Language :: Python :: 2
Classifier: Programming Language :: Python :: 2.7
Classifier: Programming Language :: Python :: 3
Classifier: Programming Language :: Python :: 3.6
Classifier: Programming Language :: Python :: 3.7
Classifier: Programming Language :: Python :: 3.8
Classifier: Programming Language :: Python :: 3.9
Classifier: Programming Language :: Python :: 3.10
Classifier: Programming Language :: Python :: 3.11
Classifier: Programming Language :: Python :: 3.12
Classifier: License :: OSI Approved :: MIT License
Classifier: Operating System :: OS Independent
Requires-Python: >=2.7
License-File: LICENSE
Requires-Dist: requests>=2.20.0
Requires-Dist: pandas>=0.24.0
Provides-Extra: python2
Requires-Dist: requests<3.0.0,>=2.20.0; extra == "python2"
Requires-Dist: pandas<1.0.0,>=0.24.0; extra == "python2"
Provides-Extra: python3
Requires-Dist: requests>=2.25.0; extra == "python3"
Requires-Dist: pandas>=1.1.0; extra == "python3"
Dynamic: author
Dynamic: home-page
Dynamic: license-file
Dynamic: requires-python
